xecs-0.9.0.dist-info/METADATA
xecs-0.9.0.dist-info/WHEEL
xecs/_internal/time.py
xecs/_internal/world.py
xecs/_internal/systems.py
xecs/_internal/simulation_app.py
xecs/_internal/query.py
xecs/_internal/transform2.py
xecs/_internal/int_.py
xecs/_internal/events.py
xecs/_internal/resource.py
xecs/_internal/__init__.py
xecs/_internal/float32.py
xecs/_internal/float_.py
xecs/_internal/input.py
xecs/_internal/int32.py
xecs/_internal/component.py
xecs/_internal/bool_.py
xecs/_internal/py_field.py
xecs/_internal/vec2.py
xecs/_internal/commands.py
xecs/_internal/struct.py
xecs/_internal/real_time_app.py
xecs/__init__.py
xecs/xecs.pyi
xecs/py.typed
xecs/xecs.cpython-311-darwin.so
xecs-0.9.0.dist-info/RECORD
