Metadata-Version: 2.1
Name: xecs
Version: 0.9.0
Classifier: Programming Language :: Rust
Classifier: Programming Language :: Python :: Implementation :: CPython
Classifier: Programming Language :: Python :: Implementation :: PyPy
Requires-Dist: numpy
Requires-Dist: black; extra == 'dev'
Requires-Dist: ruff; extra == 'dev'
Requires-Dist: mypy; extra == 'dev'
Requires-Dist: pygame; extra == 'dev'
Requires-Dist: pygame-widgets; extra == 'dev'
Requires-Dist: pytest; extra == 'dev'
Requires-Dist: pytest-benchmark; extra == 'dev'
Requires-Dist: pytest-cov; extra == 'dev'
Requires-Dist: sphinx; extra == 'dev'
Requires-Dist: sphinx-copybutton; extra == 'dev'
Requires-Dist: furo; extra == 'dev'
Requires-Dist: xecs-pygame; extra == 'dev'
Requires-Dist: sphinxcontrib-youtube; extra == 'dev'
Provides-Extra: dev
Summary: A fast and ergonomic ECS library for Python, written in Rust.
Requires-Python: >=3.11
Project-URL: github, https://github.com/lukasturcani/xecs
Project-URL: documentation, https://xecs.readthedocs.io
